yt_monk/__init__.py
yt_monk/__main__.py
yt_monk/cli.py
yt_monk/yt_monk.py
yt_monk-0.1.1a2.dist-info/LICENSE.txt
yt_monk-0.1.1a2.dist-info/METADATA
yt_monk-0.1.1a2.dist-info/WHEEL
yt_monk-0.1.1a2.dist-info/entry_points.txt
yt_monk-0.1.1a2.dist-info/top_level.txt
yt_monk-0.1.1a2.dist-info/RECORD
