Metadata-Version: 2.1
Name: yt_monk
Version: 0.1.1a2
Summary: A simple Python package for downloading videos and playlists from YouTube
Home-page: https://github.com/vojtikDortik/yt-monk
Author: Vojtech
Author-email: officialvojta@gmail.com
Keywords: youtube downloader video playlist
Classifier: Programming Language :: Python :: 3
Classifier: License :: OSI Approved :: MIT License
Classifier: Operating System :: OS Independent
Classifier: Development Status :: 3 - Alpha
Classifier: Topic :: Software Development :: Libraries :: Python Modules
Requires-Python: >=3.6
License-File: LICENSE.txt
Requires-Dist: requests>=2.24.0
Requires-Dist: pytube>=10.0.0
